fastargs/__init__.py
fastargs/config.py
fastargs/decorators.py
fastargs/dict_utils.py
fastargs/exceptions.py
fastargs/param.py
fastargs/section.py
fastargs/state.py
fastargs/validation.py
fastargs-0.3.0.dist-info/LICENSE
fastargs-0.3.0.dist-info/WHEEL
fastargs-0.3.0.dist-info/METADATA
fastargs-0.3.0.dist-info/RECORD
