Metadata-Version: 2.1
Name: fastargs
Version: 0.3.0
Summary: fastargs
Home-page: https://github.com/GuillaumeLeclerc/fastargs
Author: Guillaume Leclerc
Author-email: leclerc@mit.edu
Classifier: License :: OSI Approved :: MIT License
Requires-Dist: terminaltables
Requires-Dist: pyyaml
